examples/__init__.py
examples/properties.py
examples/shared_subscriptions.py
examples/will_message.py
gmqtt/__init__.py
gmqtt/client.py
gmqtt/storage.py
gmqtt/mqtt/__init__.py
gmqtt/mqtt/connection.py
gmqtt/mqtt/constants.py
gmqtt/mqtt/handler.py
gmqtt/mqtt/package.py
gmqtt/mqtt/property.py
gmqtt/mqtt/protocol.py
gmqtt/mqtt/utils.py
tests/__init__.py
tests/test_mqtt5.py
tests/utils.py
gmqtt-0.6.16.dist-info/LICENSE
gmqtt-0.6.16.dist-info/METADATA
gmqtt-0.6.16.dist-info/WHEEL
gmqtt-0.6.16.dist-info/top_level.txt
gmqtt-0.6.16.dist-info/zip-safe
gmqtt-0.6.16.dist-info/RECORD
