Metadata-Version: 2.1
Name: gmqtt
Version: 0.6.16
Summary: Client for MQTT protocol
Home-page: https://github.com/wialon/gmqtt
Download-URL: https://github.com/wialon/gmqtt
Author: Mikhail Turchunovich
Author-email: mitu@gurtam.com
License: MIT
Keywords: Gurtam MQTT client.
Classifier: Development Status :: 5 - Production/Stable
Classifier: Intended Audience :: Developers
Classifier: License :: OSI Approved :: MIT License
Classifier: Natural Language :: English
Classifier: Operating System :: OS Independent
Classifier: Programming Language :: Python
Classifier: Topic :: Software Development :: Libraries :: Python Modules
Requires-Python: >=3.5
Provides-Extra: test
License-File: LICENSE
